pypbr/__init__.py
pypbr/_version.py
pypbr/io.py
pypbr/material.py
pypbr/models.py
pypbr/utils.py
pypbr/blending/__init__.py
pypbr/blending/blending.py
pypbr/blending/functional.py
pypbr-0.1.0a5.dist-info/LICENSE
pypbr-0.1.0a5.dist-info/METADATA
pypbr-0.1.0a5.dist-info/WHEEL
pypbr-0.1.0a5.dist-info/top_level.txt
pypbr-0.1.0a5.dist-info/RECORD
