Metadata-Version: 2.1
Name: pypbr
Version: 0.1.0a5
Summary: A Python library for easy and fast manipulation of PBR materials with PyTorch integration.
Author-email: Giuseppe Vecchio <giuseppevecchio@hotmail.com>
License: MIT License
Project-URL: Homepage, https://github.com/giuvecchio/pypbr
Keywords: PBR,materials,PyTorch,graphics
Classifier: Programming Language :: Python :: 3
Classifier: Topic :: Multimedia :: Graphics :: 3D Modeling
Classifier: License :: OSI Approved :: MIT License
Classifier: Operating System :: OS Independent
Requires-Python: >=3.6
License-File: LICENSE
Requires-Dist: torch>=1.7.0
Requires-Dist: torchvision>=0.8.0
Requires-Dist: numpy>=1.18.0
Requires-Dist: Pillow>=8.0.0
